cellz/__about__.py
cellz/__init__.py
cellz/__main__.py
cellz/cli/__init__.py
cellz/cli/interpreter.py
cellz-1.1.0.dist-info/METADATA
cellz-1.1.0.dist-info/WHEEL
cellz-1.1.0.dist-info/entry_points.txt
cellz-1.1.0.dist-info/licenses/LICENSE.txt
cellz-1.1.0.dist-info/RECORD
